gqlpycgen/__init__.py
gqlpycgen/api.py
gqlpycgen/client.py
gqlpycgen/loader.py
gqlpycgen/models.py
gqlpycgen/utils.py
wf_gqlpycgen-0.7.4.dist-info/entry_points.txt
wf_gqlpycgen-0.7.4.dist-info/LICENSE
wf_gqlpycgen-0.7.4.dist-info/WHEEL
wf_gqlpycgen-0.7.4.dist-info/METADATA
wf_gqlpycgen-0.7.4.dist-info/RECORD
